<?xml version="1.0"?>
<mateconf>
	<entry name="command_window_screenshot" mtime="1367786905" schema="/schemas/apps/marco/keybinding_commands/command_window_screenshot" type="string">
		<stringvalue>mate-screenshot --window</stringvalue>
	</entry>
	<entry name="command_screenshot" mtime="1367786905" schema="/schemas/apps/marco/keybinding_commands/command_screenshot" type="string">
		<stringvalue>mate-screenshot</stringvalue>
	</entry>
	<entry name="command_9" mtime="1367786905" schema="/schemas/apps/marco/keybinding_commands/command" type="string">
		<stringvalue></stringvalue>
	</entry>
	<entry name="command_8" mtime="1367786905" schema="/schemas/apps/marco/keybinding_commands/command" type="string">
		<stringvalue></stringvalue>
	</entry>
	<entry name="command_7" mtime="1367786905" schema="/schemas/apps/marco/keybinding_commands/command" type="string">
		<stringvalue></stringvalue>
	</entry>
	<entry name="command_6" mtime="1367786905" schema="/schemas/apps/marco/keybinding_commands/command" type="string">
		<stringvalue></stringvalue>
	</entry>
	<entry name="command_5" mtime="1367786905" schema="/schemas/apps/marco/keybinding_commands/command" type="string">
		<stringvalue></stringvalue>
	</entry>
	<entry name="command_4" mtime="1367786905" schema="/schemas/apps/marco/keybinding_commands/command" type="string">
		<stringvalue></stringvalue>
	</entry>
	<entry name="command_3" mtime="1367786905" schema="/schemas/apps/marco/keybinding_commands/command" type="string">
		<stringvalue></stringvalue>
	</entry>
	<entry name="command_2" mtime="1367786905" schema="/schemas/apps/marco/keybinding_commands/command" type="string">
		<stringvalue></stringvalue>
	</entry>
	<entry name="command_12" mtime="1367786905" schema="/schemas/apps/marco/keybinding_commands/command" type="string">
		<stringvalue></stringvalue>
	</entry>
	<entry name="command_11" mtime="1367786905" schema="/schemas/apps/marco/keybinding_commands/command" type="string">
		<stringvalue></stringvalue>
	</entry>
	<entry name="command_10" mtime="1367786905" schema="/schemas/apps/marco/keybinding_commands/command" type="string">
		<stringvalue></stringvalue>
	</entry>
	<entry name="command_1" mtime="1367786905" schema="/schemas/apps/marco/keybinding_commands/command" type="string">
		<stringvalue></stringvalue>
	</entry>
</mateconf>
