<?xml version="1.0"?>
<mateconf>
	<entry name="name_9" mtime="1367786905" schema="/schemas/apps/marco/workspace_names/name" type="string">
		<stringvalue></stringvalue>
	</entry>
	<entry name="name_8" mtime="1367786905" schema="/schemas/apps/marco/workspace_names/name" type="string">
		<stringvalue></stringvalue>
	</entry>
	<entry name="name_7" mtime="1367786905" schema="/schemas/apps/marco/workspace_names/name" type="string">
		<stringvalue></stringvalue>
	</entry>
	<entry name="name_6" mtime="1367786905" schema="/schemas/apps/marco/workspace_names/name" type="string">
		<stringvalue></stringvalue>
	</entry>
	<entry name="name_5" mtime="1367786905" schema="/schemas/apps/marco/workspace_names/name" type="string">
		<stringvalue></stringvalue>
	</entry>
	<entry name="name_4" mtime="1367786905" schema="/schemas/apps/marco/workspace_names/name" type="string">
		<stringvalue></stringvalue>
	</entry>
	<entry name="name_3" mtime="1367786905" schema="/schemas/apps/marco/workspace_names/name" type="string">
		<stringvalue></stringvalue>
	</entry>
	<entry name="name_2" mtime="1367786905" schema="/schemas/apps/marco/workspace_names/name" type="string">
		<stringvalue></stringvalue>
	</entry>
	<entry name="name_16" mtime="1367786905" schema="/schemas/apps/marco/workspace_names/name" type="string">
		<stringvalue></stringvalue>
	</entry>
	<entry name="name_15" mtime="1367786905" schema="/schemas/apps/marco/workspace_names/name" type="string">
		<stringvalue></stringvalue>
	</entry>
	<entry name="name_14" mtime="1367786905" schema="/schemas/apps/marco/workspace_names/name" type="string">
		<stringvalue></stringvalue>
	</entry>
	<entry name="name_13" mtime="1367786905" schema="/schemas/apps/marco/workspace_names/name" type="string">
		<stringvalue></stringvalue>
	</entry>
	<entry name="name_12" mtime="1367786905" schema="/schemas/apps/marco/workspace_names/name" type="string">
		<stringvalue></stringvalue>
	</entry>
	<entry name="name_11" mtime="1367786905" schema="/schemas/apps/marco/workspace_names/name" type="string">
		<stringvalue></stringvalue>
	</entry>
	<entry name="name_10" mtime="1367786905" schema="/schemas/apps/marco/workspace_names/name" type="string">
		<stringvalue></stringvalue>
	</entry>
	<entry name="name_1" mtime="1367786905" schema="/schemas/apps/marco/workspace_names/name" type="string">
		<stringvalue></stringvalue>
	</entry>
</mateconf>
