<?xml version="1.0"?>
<mateconf>
	<entry name="show_actions" mtime="1367786905" type="schema" stype="bool" owner="mate-power-manager">
		<local_schema locale="C" short_desc="If preferences and statistics items should be shown in the context menu">
			<default type="bool" value="true"/>
		</local_schema>
	</entry>
	<entry name="icon_policy" mtime="1367786905" type="schema" stype="string" owner="mate-power-manager">
		<local_schema locale="C" short_desc="When to show the notification icon">
			<default type="string">
				<stringvalue>present</stringvalue>
			</default>
			<longdesc>Display options for the notification icon. Valid options are &quot;never&quot;, &quot;low&quot;, &quot;critical&quot;, &quot;charge&quot;, &quot;present&quot; and &quot;always&quot;.</longdesc>
		</local_schema>
	</entry>
	<entry name="enable_sound" mtime="1367786905" type="schema" stype="bool" owner="mate-power-manager">
		<local_schema locale="C" short_desc="If sounds should be used">
			<default type="bool" value="true"/>
			<longdesc>If sounds should be used when the power is critically low, or inhibit requests have stopped the policy action.</longdesc>
		</local_schema>
	</entry>
</mateconf>
